latexml_html_cleaner/__init__.py
latexml_html_cleaner/clean_html.py
latexml_html_cleaner/main.py
latexml_html_cleaner-0.0.4.dist-info/AUTHORS.rst
latexml_html_cleaner-0.0.4.dist-info/LICENSE.txt
latexml_html_cleaner-0.0.4.dist-info/METADATA
latexml_html_cleaner-0.0.4.dist-info/WHEEL
latexml_html_cleaner-0.0.4.dist-info/entry_points.txt
latexml_html_cleaner-0.0.4.dist-info/top_level.txt
latexml_html_cleaner-0.0.4.dist-info/RECORD
