Metadata-Version: 2.1
Name: latexml_html_cleaner
Version: 0.0.4
Summary: Utility to clean up an html file generated by LaTeXML
Home-page: https://github.com/eelcovv/latexml-html-cleaner
Author: EVLT
Author-email: evlt@cbs.com
License: MIT
Project-URL: Documentation, https://latexml-html-cleaner.readthedocs.io/en/latest/
Platform: any
Classifier: Development Status :: 4 - Beta
Classifier: Programming Language :: Python
License-File: LICENSE.txt
License-File: AUTHORS.rst
Requires-Dist: beautifulsoup4
Requires-Dist: importlib-metadata ; python_version < "3.9"
Provides-Extra: dev
Requires-Dist: black ; extra == 'dev'
Requires-Dist: pre-commit ; extra == 'dev'
Requires-Dist: setuptools ; extra == 'dev'
Requires-Dist: setuptools-scm ; extra == 'dev'
Requires-Dist: wheel ; extra == 'dev'
Requires-Dist: tox ; extra == 'dev'
Requires-Dist: pytest ; extra == 'dev'
Requires-Dist: pytest-pep8 ; extra == 'dev'
Requires-Dist: pytest-cov ; extra == 'dev'
Provides-Extra: testing
Requires-Dist: setuptools ; extra == 'testing'
Requires-Dist: pytest ; extra == 'testing'
Requires-Dist: pytest-pep8 ; extra == 'testing'
Requires-Dist: pytest-cov ; extra == 'testing'
Requires-Dist: tox ; extra == 'testing'
